CHANGES.rst
MANIFEST.in
README.rst
setup.cfg
setup.py
docs/README
docs/_images/README
docs/_images/preview_font.png
docs/_images/setup_select_add_on.png
docs/source/conf.py
docs/source/configuration.rst
docs/source/index.rst
docs/source/_static/logo.png
docs/source/_templates/empty
src/ps/__init__.py
src/ps.plone.realestatefont.egg-info/PKG-INFO
src/ps.plone.realestatefont.egg-info/SOURCES.txt
src/ps.plone.realestatefont.egg-info/dependency_links.txt
src/ps.plone.realestatefont.egg-info/entry_points.txt
src/ps.plone.realestatefont.egg-info/namespace_packages.txt
src/ps.plone.realestatefont.egg-info/not-zip-safe
src/ps.plone.realestatefont.egg-info/requires.txt
src/ps.plone.realestatefont.egg-info/top_level.txt
src/ps/plone/__init__.py
src/ps/plone/realestatefont/__init__.py
src/ps/plone/realestatefont/config.py
src/ps/plone/realestatefont/configure.zcml
src/ps/plone/realestatefont/interfaces.py
src/ps/plone/realestatefont/migration.py
src/ps/plone/realestatefont/plone.zcml
src/ps/plone/realestatefont/plone_views.py
src/ps/plone/realestatefont/profiles.zcml
src/ps/plone/realestatefont/psplonerealestate-preview.pt
src/ps/plone/realestatefont/setuphandlers.py
src/ps/plone/realestatefont/testing.py
src/ps/plone/realestatefont/fonts_resources/README.md
src/ps/plone/realestatefont/fonts_resources/index.html
src/ps/plone/realestatefont/fonts_resources/styles.css
src/ps/plone/realestatefont/fonts_resources/fonts/iconmagic.eot
src/ps/plone/realestatefont/fonts_resources/fonts/iconmagic.svg
src/ps/plone/realestatefont/fonts_resources/fonts/iconmagic.ttf
src/ps/plone/realestatefont/fonts_resources/fonts/iconmagic.woff
src/ps/plone/realestatefont/locales/manual.pot
src/ps/plone/realestatefont/locales/plone.pot
src/ps/plone/realestatefont/locales/ps.plone.realestatefont.pot
src/ps/plone/realestatefont/locales/en/LC_MESSAGES/ps.plone.realestatefont.po
src/ps/plone/realestatefont/profiles/base/metadata.xml
src/ps/plone/realestatefont/profiles/plone4/browserlayer.xml
src/ps/plone/realestatefont/profiles/plone4/cssregistry.xml
src/ps/plone/realestatefont/profiles/plone4/metadata.xml
src/ps/plone/realestatefont/profiles/plone5/browserlayer.xml
src/ps/plone/realestatefont/profiles/plone5/metadata.xml
src/ps/plone/realestatefont/profiles/plone5/registry.xml
src/ps/plone/realestatefont/profiles/uninstall-base/browserlayer.xml
src/ps/plone/realestatefont/profiles/uninstall-plone4/metadata.xml
